quackamollie/model/langchain_simple/__init__.py
quackamollie/model/langchain_simple/model_langchain_simple.py
quackamollie/model/langchain_simple/prompt/__init__.py
quackamollie/model/langchain_simple/prompt/langchain_simple_prompt.py
quackamollie_model_langchain_simple-0.1.dist-info/LICENSE
quackamollie_model_langchain_simple-0.1.dist-info/METADATA
quackamollie_model_langchain_simple-0.1.dist-info/WHEEL
quackamollie_model_langchain_simple-0.1.dist-info/entry_points.txt
quackamollie_model_langchain_simple-0.1.dist-info/top_level.txt
quackamollie_model_langchain_simple-0.1.dist-info/RECORD
